r9s/__init__.py
r9s/_version.py
r9s/audio_sdk.py
r9s/basesdk.py
r9s/chat.py
r9s/client.py
r9s/completions.py
r9s/edits.py
r9s/embeddings.py
r9s/engine_embeddings.py
r9s/httpclient.py
r9s/images.py
r9s/messages.py
r9s/models_.py
r9s/moderations.py
r9s/proxy.py
r9s/py.typed
r9s/responses.py
r9s/sdk.py
r9s/sdkconfiguration.py
r9s/search.py
r9s/_hooks/__init__.py
r9s/_hooks/registration.py
r9s/_hooks/sdkhooks.py
r9s/_hooks/types.py
r9s/agents/__init__.py
r9s/agents/exceptions.py
r9s/agents/local_store.py
r9s/agents/models.py
r9s/agents/store.py
r9s/agents/template.py
r9s/agents/versioning.py
r9s/cli_tools/__init__.py
r9s/cli_tools/agent_cli.py
r9s/cli_tools/audio_cli.py
r9s/cli_tools/bot_cli.py
r9s/cli_tools/bots.py
r9s/cli_tools/chat_cli.py
r9s/cli_tools/chat_extensions.py
r9s/cli_tools/cli.py
r9s/cli_tools/command_cli.py
r9s/cli_tools/commands.py
r9s/cli_tools/completion_cli.py
r9s/cli_tools/config.py
r9s/cli_tools/i18n.py
r9s/cli_tools/image_cli.py
r9s/cli_tools/models_cli.py
r9s/cli_tools/run_cli.py
r9s/cli_tools/skill_cli.py
r9s/cli_tools/stream_timing.py
r9s/cli_tools/template_renderer.py
r9s/cli_tools/update_check.py
r9s/cli_tools/tools/__init__.py
r9s/cli_tools/tools/base.py
r9s/cli_tools/tools/claude_code.py
r9s/cli_tools/tools/codex.py
r9s/cli_tools/tools/qwen_code.py
r9s/cli_tools/tools/registry.py
r9s/cli_tools/ui/__init__.py
r9s/cli_tools/ui/banner.py
r9s/cli_tools/ui/chat_prompt.py
r9s/cli_tools/ui/home.py
r9s/cli_tools/ui/prompts.py
r9s/cli_tools/ui/rich_output.py
r9s/cli_tools/ui/spinner.py
r9s/cli_tools/ui/terminal.py
r9s/errors/__init__.py
r9s/errors/authenticationerror.py
r9s/errors/badrequesterror.py
r9s/errors/internalservererror.py
r9s/errors/no_response_error.py
r9s/errors/notfounderror.py
r9s/errors/permissiondeniederror.py
r9s/errors/r9sdefaulterror.py
r9s/errors/r9serror.py
r9s/errors/ratelimiterror.py
r9s/errors/responsevalidationerror.py
r9s/errors/serviceunavailableerror.py
r9s/errors/unprocessableentityerror.py
r9s/models/__init__.py
r9s-0.9.0.dist-info/licenses/LICENSE
r9s-0.9.0.dist-info/METADATA
r9s-0.9.0.dist-info/WHEEL
r9s-0.9.0.dist-info/entry_points.txt
r9s-0.9.0.dist-info/top_level.txt
r9s-0.9.0.dist-info/RECORD
