Metadata-Version: 2.4
Name: r9s
Version: 0.9.0
Summary: The official Python library for the r9s API
Author: routertokens
License-Expression: MIT
Project-URL: Homepage, https://github.com/r9s-ai/r9s-python
Project-URL: Repository, https://github.com/r9s-ai/r9s-python
Project-URL: Issues, https://github.com/r9s-ai/r9s-python/issues
Classifier: Development Status :: 3 - Alpha
Classifier: Intended Audience :: Developers
Classifier: Programming Language :: Python :: 3
Classifier: Programming Language :: Python :: 3.11
Classifier: Programming Language :: Python :: 3.12
Classifier: Programming Language :: Python :: 3.13
Requires-Python: >=3.11
License-File: LICENSE
Requires-Dist: httpcore>=1.0.9
Requires-Dist: httpx>=0.28.1
Requires-Dist: prompt-toolkit>=3.0.0
Requires-Dist: pydantic>=2.11.2
Requires-Dist: pyyaml>=6.0
Requires-Dist: python-dotenv>=1.0.1
Requires-Dist: tomli-w>=1.0.0
Provides-Extra: test
Requires-Dist: pytest; extra == "test"
Requires-Dist: pytest-asyncio; extra == "test"
Provides-Extra: dev
Requires-Dist: mypy==1.15.0; extra == "dev"
Requires-Dist: pre-commit>=3.7.0; extra == "dev"
Requires-Dist: pylint==3.2.3; extra == "dev"
Requires-Dist: pyright==1.1.398; extra == "dev"
Requires-Dist: ruff>=0.14.10; extra == "dev"
Provides-Extra: rich
Requires-Dist: rich>=13.0; extra == "rich"
Dynamic: license-file
